breeze_connect/__init__.py
breeze_connect/breeze_connect.py
breeze_connect-1.0.13.dist-info/LICENSE
breeze_connect-1.0.13.dist-info/METADATA
breeze_connect-1.0.13.dist-info/WHEEL
breeze_connect-1.0.13.dist-info/top_level.txt
breeze_connect-1.0.13.dist-info/RECORD
