Metadata-Version: 2.1
Name: breeze-connect
Version: 1.0.13
Summary: ICICI Direct Breeze
Home-page: https://github.com/pypa/sampleproject
Author: ICICI Direct Breeze
Author-email: breezeapi@icicisecurities.com
License: UNKNOWN
Platform: UNKNOWN
Classifier: Programming Language :: Python :: 3
Classifier: License :: OSI Approved :: MIT License
Classifier: Operating System :: OS Independent
Requires-Python: >=3.6
